rescue_api/__init__.py
rescue_api/rescuetime.py
rescue_api/run_tests.py
rescue_api-1.0.3.dist-info/LICENSE
rescue_api-1.0.3.dist-info/METADATA
rescue_api-1.0.3.dist-info/WHEEL
rescue_api-1.0.3.dist-info/top_level.txt
rescue_api-1.0.3.dist-info/RECORD
