Metadata-Version: 2.1
Name: rescue-api
Version: 1.0.3
Summary: A Python wrapper for the RescueTime API.
Home-page: https://git.sr.ht/~mjorgensen/rescue-api
Author: Matthew Jorgensen
Author-email: matthew@jrgnsn.net
License: UNKNOWN
Platform: UNKNOWN
Classifier: Programming Language :: Python :: 3
Classifier: License :: OSI Approved :: MIT License
Classifier: Operating System :: OS Independent
License-File: LICENSE
Requires-Dist: requests
